bsccm/__init__.py
bsccm/_version.py
bsccm/bsccm.py
bsccm/led_array_calibration.py
bsccm/quasi_dome_design.json
bsccm/fluorescence_processing/__init__.py
bsccm/fluorescence_processing/demixing_util.py
bsccm/fluorescence_processing/fluor_display.py
bsccm/fluorescence_processing/gating_util.py
bsccm/fluorescence_processing/shading_correction_util.py
bsccm/phase/__init__.py
bsccm/phase/functional_dpc.py
bsccm/phase/util.py
bsccm-1.2.0.dist-info/LICENSE
bsccm-1.2.0.dist-info/METADATA
bsccm-1.2.0.dist-info/WHEEL
bsccm-1.2.0.dist-info/top_level.txt
bsccm-1.2.0.dist-info/RECORD
