Metadata-Version: 2.1
Name: bsccm
Version: 1.2.0
Summary: Access the Berkeley Single Cell Computational Microscopy
Home-page: https://github.com/henrypinkard/BSCCM
Author: Henry Pinkard
Author-email: henry.pinkard@gmail.com
Classifier: License :: OSI Approved :: BSD License
Classifier: Operating System :: OS Independent
Requires-Python: >=3.6
License-File: LICENSE
Requires-Dist: numpy
Requires-Dist: pandas
Requires-Dist: zarr
Requires-Dist: requests
Requires-Dist: tqdm
